Metadata-Version: 2.1
Name: rzLyricFind
Version: 1.0.0
Summary: Easy Way To find lyric
Home-page: https://github.com/indobyte/rzLyricFind
Author: Reza
Author-email: neobyteid@gmail.com
License: UNKNOWN
Keywords: pypi,python,automation,cicd,lyricFind,rzLyricFind
Platform: UNKNOWN
Classifier: Development Status :: 1 - Planning
Classifier: Intended Audience :: Developers
Classifier: Programming Language :: Python :: 3
Classifier: Operating System :: Unix
Classifier: Operating System :: MacOS :: MacOS X
Classifier: Operating System :: Microsoft :: Windows
